switchkeys/api/models/auth.py
switchkeys/api/models/organization.py
switchkeys/api/models/project.py
switchkeys/api/models/user.py
switchkeys/api/request/request.py
switchkeys/api/request/types.py
switchkeys/api/response/response.py
switchkeys/api/response/types.py
switchkeys/api/routes.py
switchkeys/api/types.py
switchkeys/core/base.py
switchkeys/core/exceptions.py
switchkeys/utils/config.py
switchkeys/utils/decorators.py
switchkeys/utils/logger.py
switchkeys/utils/parser.py
switchkeys-0.1.2.dist-info/LICENSE
switchkeys-0.1.2.dist-info/METADATA
switchkeys-0.1.2.dist-info/WHEEL
switchkeys-0.1.2.dist-info/RECORD
