Metadata-Version: 2.1
Name: switchkeys
Version: 0.1.2
Summary: The SwitchKeys Python client enables seamless integration with the SwitchKeys feature management platform in Python applications. Developers can effortlessly incorporate feature flags and toggle management into their projects, accessing user data, retrieving feature values, and setting feature flags with ease. This client streamlines the process of implementing feature management functionality, empowering developers to efficiently control feature rollout and experimentation in their app
Author: Mahmoud Emad
Author-email: mahmmoud.hassanein@gmail.com
Requires-Python: >=3.10,<4.0
Classifier: Programming Language :: Python :: 3
Classifier: Programming Language :: Python :: 3.10
Classifier: Programming Language :: Python :: 3.11
Classifier: Programming Language :: Python :: 3.12
Requires-Dist: configparser (>=6.0.1,<7.0.0)
Requires-Dist: requests (>=2.31.0,<3.0.0)
